networkxx/__init__.py
networkxx/docs.py
networkxx/graph.py
networkxx/io.py
networkxx/tree.py
networkxx-1.0.0.dist-info/METADATA
networkxx-1.0.0.dist-info/WHEEL
networkxx-1.0.0.dist-info/top_level.txt
networkxx-1.0.0.dist-info/RECORD
